{
	"textures": [
		{
			"image": "hopups.png",
			"format": "RGBA8888",
			"size": {
				"w": 37,
				"h": 111
			},
			"scale": 1,
			"frames": [
				{
					"filename": "00.png",
					"rotated": false,
					"trimmed": false,
					"sourceSize": {
						"w": 35,
						"h": 35
					},
					"spriteSourceSize": {
						"x": 0,
						"y": 0,
						"w": 35,
						"h": 35
					},
					"frame": {
						"x": 1,
						"y": 1,
						"w": 35,
						"h": 35
					}
				},
				{
					"filename": "01.png",
					"rotated": false,
					"trimmed": false,
					"sourceSize": {
						"w": 35,
						"h": 35
					},
					"spriteSourceSize": {
						"x": 0,
						"y": 0,
						"w": 35,
						"h": 35
					},
					"frame": {
						"x": 1,
						"y": 38,
						"w": 35,
						"h": 35
					}
				},
				{
					"filename": "02.png",
					"rotated": false,
					"trimmed": false,
					"sourceSize": {
						"w": 35,
						"h": 35
					},
					"spriteSourceSize": {
						"x": 0,
						"y": 0,
						"w": 35,
						"h": 35
					},
					"frame": {
						"x": 1,
						"y": 75,
						"w": 35,
						"h": 35
					}
				}
			]
		}
	],
	"meta": {
		"app": "http://free-tex-packer.com",
		"version": "0.6.6"
	}
}